README.rst
setup.py
tsuru/__init__.py
tsuru/plugins/__init__.py
tsuru/plugins/statsd.py
tsuru/plugins/stats/__init__.py
tsuru/plugins/stats/fake.py
tsuru/plugins/stats/logstash.py
tsuru/plugins/stats/statsd.py
tsuru/stream/__init__.py
tsuru/tests/__init__.py
tsuru/tests/hooks/__init__.py
tsuru/tests/plugins/__init__.py
tsuru/tests/plugins/test_logstash.py
tsuru/tests/plugins/test_procfile_watcher.py
tsuru/tests/plugins/test_stats.py
tsuru/tests/plugins/test_statsd.py
tsuru/tests/plugins/test_status_reporter.py
tsuru_circus.egg-info/PKG-INFO
tsuru_circus.egg-info/SOURCES.txt
tsuru_circus.egg-info/dependency_links.txt
tsuru_circus.egg-info/requires.txt
tsuru_circus.egg-info/top_level.txt