Metadata-Version: 1.0
Name: tsuru-circus
Version: 0.8.16
Summary: Circus extensions for tsuru.
Home-page: https://github.com/tsuru/tsuru-circus
Author: timeredbull
Author-email: timeredbull@corp.globo.com
License: UNKNOWN
Platform: UNKNOWN
